recall.py
recall_cmds-0.0.2.dist-info/DESCRIPTION.rst
recall_cmds-0.0.2.dist-info/METADATA
recall_cmds-0.0.2.dist-info/RECORD
recall_cmds-0.0.2.dist-info/WHEEL
recall_cmds-0.0.2.dist-info/entry_points.txt
recall_cmds-0.0.2.dist-info/metadata.json
recall_cmds-0.0.2.dist-info/top_level.txt
