Metadata-Version: 2.0
Name: recall-cmds
Version: 0.0.2
Summary: A tool to view and edit templated commands that you forget.
Home-page: https://github.com/mavcook/recall
Author: Maverick Cook
Author-email: mav@mavcook.com
License: UNKNOWN
Platform: UNKNOWN
Classifier: Development Status :: 3 - Alpha
Classifier: Environment :: Console
Classifier: Programming Language :: Python :: 3
Classifier: Programming Language :: Python :: 3.3
Classifier: Programming Language :: Python :: 3.4
Classifier: Programming Language :: Python :: 3.5
Classifier: Programming Language :: Python :: 3.6
Requires-Python: >=3
